{
  "kind": "collectionType",
  "collectionName": "stafs",
  "info": {
    "singularName": "staf",
    "pluralName": "stafs",
    "displayName": "Staf"
  },
  "options": {
    "draftAndPublish": true
  },
  "pluginOptions": {},
  "attributes": {
    "name": {
      "type": "string"
    },
    "position": {
      "type": "string"
    },
    "bio": {
      "type": "text"
    },
    "image": {
      "type": "media",
      "multiple": false,
      "allowedTypes": [
        "images",
        "files",
        "videos",
        "audios"
      ]
    },
    "order": {
      "type": "integer"
    }
  }
}
